django_jsonapi_framework/__init__.py
django_jsonapi_framework/conf.py
django_jsonapi_framework/emails.py
django_jsonapi_framework/exceptions.py
django_jsonapi_framework/models.py
django_jsonapi_framework/schema.json
django_jsonapi_framework/utils.py
django_jsonapi_framework/views.py
django_jsonapi_framework/auth/__init__.py
django_jsonapi_framework/auth/apps.py
django_jsonapi_framework/auth/conf.py
django_jsonapi_framework/auth/models.py
django_jsonapi_framework/auth/permissions.py
django_jsonapi_framework/auth/utils.py
django_jsonapi_framework/auth/views.py
django_jsonapi_framework/auth/migrations/0001_initial.py
django_jsonapi_framework/auth/migrations/__init__.py
django_jsonapi_framework-0.0.5.dist-info/METADATA
django_jsonapi_framework-0.0.5.dist-info/WHEEL
django_jsonapi_framework-0.0.5.dist-info/licenses/LICENSE.md
django_jsonapi_framework-0.0.5.dist-info/RECORD
